<annotation>
	<folder>image</folder>
	<filename>cardboard14.jpg</filename>
	<path>G:\&#22823;&#21019;&#39033;&#30446;\image\cardboard14.jpg</path>
	<source>
		<database>Unknown</database>
	</source>
	<size>
		<width>512</width>
		<height>384</height>
		<depth>3</depth>
	</size>
	<segmented>0</segmented>
	<object>
		<name>cardboard</name>
		<pose>Unspecified</pose>
		<truncated>0</truncated>
		<difficult>0</difficult>
		<bndbox>
			<xmin>118</xmin>
			<ymin>84</ymin>
			<xmax>272</xmax>
			<ymax>358</ymax>
		</bndbox>
	</object>
</annotation>